<?xml version="1.0" encoding="utf-8"?>
<manifest>
	<control namespace="QuestionnaireDesigner" constructor="QuestionnaireDesignerControl" version="0.0.17" display-name-key="QuestionnaireDesignerControl" description-key="QuestionnaireDesignerControl description" control-type="virtual">
		<property name="questionnaireDesigner" display-name-key="Questionnaire Designer" description-key="Questionnaire Designer" of-type="Multiple" usage="bound" required="true" />
		<resources>
			<code path="index.ts" order="1" />
			<css path="css/index.css" />
			<platform-library name="React" version="16.14.0" />
			<platform-library name="Fluent" version="9.46.2" />
		</resources>
		<feature-usage>
			<uses-feature name="Utility" required="true" />
			<uses-feature name="WebAPI" required="true" />
		</feature-usage>
	</control>
</manifest>
